Metadata-Version: 1.1
Name: abstractfactory
Version: 1.0.3
Summary: Abstract Factory functionality for Python
Home-page: https://github.com/davidbetz/pyabstractfactory
Author: David Betz
Author-email: dfb@davidbetz.net
License: UNKNOWN
Keywords: abstract-factory,patterns
Platform: UNKNOWN
Classifier: Intended Audience :: Developers
Classifier: Topic :: Software Development :: Build Tools
Classifier: License :: OSI Approved :: MIT License
Classifier: Programming Language :: Python :: 2.7
Classifier: Programming Language :: Python :: 3.6
